easyfab/__init__.py
easyfab/api.py
easyfab/base.py
easyfab/commands.py
easyfab/decorators.py
easyfab/errors.py
easyfab/items.py
easyfab/utils.py
easyfab/templates/deployment.py
easyfab/templates/fabfile.py
easyfab/templates/deployment/conf/apache.conf
easyfab/templates/deployment/conf/nginx.conf
easyfab/templates/deployment/conf/supervisor.conf
easyfab-0.4.12.data/data/LICENSE
easyfab-0.4.12.data/data/README.rst
easyfab-0.4.12.data/scripts/easyfab
easyfab-0.4.12.dist-info/DESCRIPTION.rst
easyfab-0.4.12.dist-info/METADATA
easyfab-0.4.12.dist-info/RECORD
easyfab-0.4.12.dist-info/WHEEL
easyfab-0.4.12.dist-info/metadata.json
easyfab-0.4.12.dist-info/top_level.txt
