Metadata-Version: 2.0
Name: easyfab
Version: 0.4.12
Summary: Simple deployments with fabric
Home-page: https://github.com/phonkee/easyfab/
Author: phonkee
Author-email: phonkee@phonkee.eu
License: Copyright 2013 Peter Vrba
Requires-Dist: fabric
Requires-Dist: jinja2
Requires-Dist: unipath
